ezbloom/__init__.py
easybloom-0.1.4.dist-info/LICENSE.txt
easybloom-0.1.4.dist-info/METADATA
easybloom-0.1.4.dist-info/WHEEL
easybloom-0.1.4.dist-info/top_level.txt
easybloom-0.1.4.dist-info/RECORD
