Metadata-Version: 2.1
Name: easybloom
Version: 0.1.4
Summary: Simplifies using bloom ai. Brings it down to only 1 line of code.
Author: Abbott Broughton
Author-email: abbottbroughton@icloud.com
License: The Unlicense
Classifier: Programming Language :: Python :: 3.7
Classifier: Programming Language :: Python :: 3.8
Classifier: Programming Language :: Python :: 3.9
Classifier: Programming Language :: Python :: 3.10
Classifier: Programming Language :: Python :: 3.11
License-File: LICENSE.txt
Requires-Dist: requests
